layers/GeM.py
layers/LocalBranch.py
layers/OrtholFusion.py
layers/__init__.py
models/DOLG.py
models/__init__.py
dolg_tensorflow-0.0.1.dist-info/LICENSE
dolg_tensorflow-0.0.1.dist-info/METADATA
dolg_tensorflow-0.0.1.dist-info/WHEEL
dolg_tensorflow-0.0.1.dist-info/top_level.txt
dolg_tensorflow-0.0.1.dist-info/RECORD
