Metadata-Version: 2.1
Name: dolg-tensorflow
Version: 0.0.1
Summary: Deep Orthogonal Fusion of Local and Global Features (DOLG) - TensorFlow 2 (Keras)
Home-page: https://github.com/innat/DOLG-TensorFlow
Author: M.Innat
Author-email: innat1994@gmail.com
License: MIT
Keywords: deep learning,image retrieval,image recognition
Platform: UNKNOWN
Classifier: Development Status :: 1 - Planning
Classifier: Intended Audience :: Developers
Classifier: Topic :: Scientific/Engineering :: Artificial Intelligence
Classifier: License :: OSI Approved :: MIT License
Classifier: Programming Language :: Python :: 3.7
License-File: LICENSE
Requires-Dist: opencv-python (>=4.1.2)
Requires-Dist: tensorflow (>=2.7)
Requires-Dist: tensorflow-addons (>=0.15.0)
